gwwapi/__init__.py
gwwapi/client.py
gwwapi/utils.py
gwwapi-0.0.2.dist-info/LICENSE
gwwapi-0.0.2.dist-info/METADATA
gwwapi-0.0.2.dist-info/WHEEL
gwwapi-0.0.2.dist-info/top_level.txt
gwwapi-0.0.2.dist-info/RECORD
