Metadata-Version: 2.1
Name: gwwapi
Version: 0.0.2
Summary: A python package for using the Global Water Watch API
Home-page: https://github.com/global-water-watch/gww-api
Author: Jurian Beunk
Author-email: jurianbeunk@gmail.com
License: MIT
Classifier: License :: OSI Approved :: MIT License
Classifier: Programming Language :: Python :: 3.8
License-File: LICENSE
Requires-Dist: geopandas
Requires-Dist: pandas
Requires-Dist: requests
Requires-Dist: shapely
